flet_multi_page/__init__.py
flet_multi_page/sub_page.py
flet_multi_page-1.3.1.dist-info/LICENSE
flet_multi_page-1.3.1.dist-info/METADATA
flet_multi_page-1.3.1.dist-info/WHEEL
flet_multi_page-1.3.1.dist-info/top_level.txt
flet_multi_page-1.3.1.dist-info/RECORD
